pymoku/__init__.py
pymoku/_arbwavegen.py
pymoku/_bode_analyzer.py
pymoku/_datalogger.py
pymoku/_dec_filter.py
pymoku/_embedded_pll.py
pymoku/_firfilter.py
pymoku/_frame_instrument.py
pymoku/_frame_instrument_data.py
pymoku/_frequency_response_analyzer.py
pymoku/_frequency_response_analyzer_data.py
pymoku/_iir_block.py
pymoku/_iirfilterbox.py
pymoku/_input_instrument.py
pymoku/_instrument.py
pymoku/_laser_lock_box.py
pymoku/_lockinamp.py
pymoku/_oscilloscope.py
pymoku/_oscilloscope_data.py
pymoku/_phasemeter.py
pymoku/_pid.py
pymoku/_pid_controller.py
pymoku/_specan.py
pymoku/_specan_data.py
pymoku/_stream_instrument.py
pymoku/_sweep_generator.py
pymoku/_trigger.py
pymoku/_utils.py
pymoku/_waveform_generator.py
pymoku/dataparser.py
pymoku/finders.py
pymoku/instruments.py
pymoku/li.capnp
pymoku/plotly_support.py
pymoku/pybj_test.py
pymoku/pybonjour.py
pymoku/version.py
pymoku/version.txt
pymoku/data/000
pymoku/data/001
pymoku/data/index
pymoku/tools/__init__.py
pymoku/tools/compat.py
pymoku/tools/moku.py
pymoku/tools/moku_convert.py
pymoku-2.8.3.dist-info/METADATA
pymoku-2.8.3.dist-info/RECORD
pymoku-2.8.3.dist-info/WHEEL
pymoku-2.8.3.dist-info/entry_points.txt
pymoku-2.8.3.dist-info/top_level.txt
