Metadata-Version: 2.1
Name: pymoku
Version: 2.8.3
Summary: UNKNOWN
Home-page: https://github.com/liquidinstruments/pymoku
Author: Ben Coughlan
Author-email: ben@liquidinstruments.com
License: MIT
Download-URL: https://github.com/liquidinstruments/pymoku/archive/2.8.3.tar.gz
Keywords: moku,liquid instruments,test,measurement,lab,equipment
Platform: UNKNOWN
Requires-Dist: future
Requires-Dist: pyzmq (>=15.3.0)
Requires-Dist: requests (>=2.18.0)
